[{"username":"nagelkilian05","uid":"google-oauth2|118171829823269176911","data":{"trainings":[],"settings":[]}},{"username":"nagelkilian05","uid":"google-oauth2|118171829823269176911","data":{"trainings":[],"settings":[]}},{"username":"nagelkilian05","uid":"google-oauth2|118171829823269176911","data":{"trainings":[],"settings":[]}},{"username":"nagelkilian05","uid":"google-oauth2|118171829823269176911","data":{"trainings":[],"settings":[]}},{"username":"nagelkilian05","uid":"google-oauth2|118171829823269176911","data":{"trainings":[],"settings":[]}},{"username":"nagelkilian05","uid":"google-oauth2|118171829823269176911","data":{"trainings":[],"settings":[]}},{"username":"nagelkilian05","uid":"google-oauth2|118171829823269176911","data":{"trainings":[],"settings":[]}},{"username":"nagelkilian05","uid":"google-oauth2|118171829823269176911","data":{"trainings":[],"settings":[]}},{"username":"nagelkilian05","uid":"google-oauth2|118171829823269176911","data":{"trainings":[],"settings":[]}},{"username":"nagelkilian05","uid":"google-oauth2|118171829823269176911","data":{"trainings":[],"settings":[]}},{"username":"nagelkilian05","uid":"google-oauth2|118171829823269176911","data":{"trainings":[],"settings":[]}},{"username":"nagelkilian05","uid":"google-oauth2|118171829823269176911","data":{"trainings":[],"settings":[]}},{"username":"nagelkilian05","uid":"google-oauth2|118171829823269176911","data":{"trainings":[],"settings":[]}},{"username":"nagelkilian05","uid":"google-oauth2|118171829823269176911","data":{"trainings":[],"settings":[]}},{"username":"nagelkilian05","uid":"google-oauth2|118171829823269176911","data":{"trainings":[],"settings":[]}},{"username":"nagelkilian05","uid":"google-oauth2|118171829823269176911","data":{"trainings":[],"settings":[]}},{"username":"nagelkilian05","uid":"google-oauth2|118171829823269176911","data":{"trainings":[],"settings":[]}},{"username":"nagelkilian05","uid":"google-oauth2|118171829823269176911","data":{"trainings":[],"settings":[]}},{"username":"nagelkilian05","uid":"google-oauth2|118171829823269176911","data":{"trainings":[],"settings":[]}},{"username":"nagelkilian05","uid":"google-oauth2|118171829823269176911","data":{"trainings":[],"settings":[]}},{"username":"nagelkilian05","uid":"google-oauth2|118171829823269176911","data":{"trainings":[],"settings":[]}},{"username":"nagelkilian05","uid":"google-oauth2|118171829823269176911","data":{"trainings":[],"settings":[]}},{"username":"nagelkilian05","uid":"google-oauth2|118171829823269176911","data":{"trainings":[],"settings":[]}},{"username":"nagelkilian05","uid":"google-oauth2|118171829823269176911","data":{"trainings":[],"settings":[]}},{"username":"nagelkilian05","uid":"google-oauth2|118171829823269176911","data":{"trainings":[],"settings":[]}},{"username":"nagelkilian05","uid":"google-oauth2|118171829823269176911","data":{"trainings":[],"settings":[]}},{"username":"nagelkilian05","uid":"google-oauth2|118171829823269176911","data":{"trainings":[],"settings":[]}},{"username":"nagelkilian05","uid":"google-oauth2|118171829823269176911","data":{"trainings":[],"settings":[]}},{"username":"nagelkilian05","uid":"google-oauth2|118171829823269176911","data":{"trainings":[],"settings":[]}},{"username":"nagelkilian05","uid":"google-oauth2|118171829823269176911","data":{"trainings":[],"settings":[]}},{"username":"nagelkilian05","uid":"google-oauth2|118171829823269176911","data":{"trainings":[],"settings":[]}},{"username":"nagelkilian05","uid":"google-oauth2|118171829823269176911","data":{"trainings":[],"settings":[]}},{"username":"nagelkilian05","uid":"google-oauth2|118171829823269176911","data":{"trainings":[],"settings":[]}},{"username":"nagelkilian05","uid":"google-oauth2|118171829823269176911","data":{"trainings":[],"settings":[]}},{"username":"perfuze1","uid":"google-oauth2|103688329274937160384","data":{"trainings":[],"settings":[]}},{"username":"nagelkilian05","uid":"google-oauth2|118171829823269176911","data":{"trainings":[],"settings":[]}},{"username":"perfuze1","uid":"google-oauth2|103688329274937160384","data":{"trainings":[],"settings":[]}},{"username":"nagelkilian05","uid":"google-oauth2|118171829823269176911","data":{"trainings":[],"settings":[]}},{"username":"perfuze1","uid":"google-oauth2|103688329274937160384","data":{"trainings":[],"settings":[]}},{"username":"nagelkilian05","uid":"google-oauth2|118171829823269176911","data":{"trainings":[],"settings":[]}},{"username":"nagelkilian05","uid":"google-oauth2|118171829823269176911","data":{"trainings":[],"settings":[]}},{"username":"perfuze1","uid":"google-oauth2|103688329274937160384","data":{"trainings":[],"settings":[]}},{"username":"nagelkilian05","uid":"google-oauth2|118171829823269176911","data":{"trainings":[],"settings":[]}},{"username":"perfuze1","uid":"google-oauth2|103688329274937160384","data":{"trainings":[],"settings":[]}},{"username":"nagelkilian05","uid":"google-oauth2|118171829823269176911","data":{"trainings":[],"settings":[]}},{"username":"perfuze1","uid":"google-oauth2|103688329274937160384","data":{"trainings":[],"settings":[]}},{"username":"nagelkilian05","uid":"google-oauth2|118171829823269176911","data":{"trainings":[],"settings":[]}},{"username":"nagelkilian05","uid":"google-oauth2|118171829823269176911","data":{"trainings":[],"settings":[]}},{"username":"nagelkilian05","uid":"google-oauth2|118171829823269176911","data":{"trainings":[],"settings":[]}},{"username":"nagelkilian05","uid":"google-oauth2|118171829823269176911","data":{"trainings":[],"settings":[]}},{"username":"nagelkilian05","uid":"google-oauth2|118171829823269176911","data":{"trainings":[],"settings":[]}},{"username":"celticheros962","uid":"google-oauth2|103076261718675721652","data":{"trainings":[],"settings":[]}},{"username":"celticheros962","uid":"google-oauth2|103076261718675721652","data":{"trainings":[],"settings":[]}},{"username":"celticheros962","uid":"google-oauth2|103076261718675721652","data":{"trainings":[],"settings":[]}},{"username":"nagelkilian05","uid":"google-oauth2|118171829823269176911","data":{"trainings":[],"settings":[]}},{"username":"nagelkilian05","uid":"google-oauth2|118171829823269176911","data":{"trainings":[],"settings":[]}},{"username":"nagelkilian05","uid":"google-oauth2|118171829823269176911","data":{"trainings":[],"settings":[]}},{"username":"nagelkilian05","uid":"google-oauth2|118171829823269176911","data":{"trainings":[],"settings":[]}},{"username":"nagelkilian05","uid":"google-oauth2|118171829823269176911","data":{"trainings":[],"settings":[]}},{"username":"perfuze1","uid":"google-oauth2|103688329274937160384","data":{"trainings":[],"settings":[]}},{"username":"nagelkilian05","uid":"google-oauth2|118171829823269176911","settings":{"darkmode":false,"layout":"default"},"data":{"trainings":[],"body":{"weight":[],"bodyfat":[]}}},{"username":"perfuze1","uid":"google-oauth2|103688329274937160384","settings":{"darkmode":false,"layout":"default"},"data":{"trainings":[],"body":{"weight":[],"bodyfat":[]}}},{"username":"perfuze1","uid":"google-oauth2|103688329274937160384","settings":{"darkmode":false,"layout":"default"},"data":{"trainings":[],"body":{"weight":[],"bodyfat":[]}}},{"username":"perfuze1","uid":"google-oauth2|103688329274937160384","settings":{"darkmode":false,"layout":"default"},"data":{"trainings":[],"body":{"weight":[],"bodyfat":[]}}},{"username":"perfuze1","uid":"google-oauth2|103688329274937160384","settings":{"darkmode":false,"layout":"default"},"data":{"trainings":[],"body":{"weight":[],"bodyfat":[]}}},{"username":"perfuze1","uid":"google-oauth2|103688329274937160384","settings":{"darkmode":false,"layout":"default"},"data":{"trainings":[],"body":{"weight":[],"bodyfat":[]}}},{"username":"perfuze1","uid":"google-oauth2|103688329274937160384","settings":{"darkmode":false,"layout":"default"},"data":{"trainings":[],"body":{"weight":[],"bodyfat":[]}}},{"username":"nagelkilian05","uid":"google-oauth2|118171829823269176911","settings":{"darkmode":false,"layout":"default"},"data":{"trainings":[],"body":{"weight":[],"bodyfat":[]}}},{"username":"nagelkilian05","uid":"google-oauth2|118171829823269176911","settings":{"darkmode":false,"layout":"default"},"data":{"trainings":[],"body":{"weight":[],"bodyfat":[]}}},{"username":"nagelkilian05","uid":"google-oauth2|118171829823269176911","settings":{"darkmode":false,"layout":"default"},"data":{"trainings":[],"body":{"weight":[],"bodyfat":[]}}},{"username":"perfuze1","uid":"google-oauth2|103688329274937160384","settings":{"darkmode":false,"layout":"default"},"data":{"trainings":[],"body":{"weight":[],"bodyfat":[]}}},{"username":"nagelkilian05","uid":"google-oauth2|118171829823269176911","settings":{"darkmode":false,"layout":"default"},"data":{"trainings":[],"body":{"weight":[],"bodyfat":[]}}},{"username":"perfuze1","uid":"google-oauth2|103688329274937160384","settings":{"darkmode":false,"layout":"default"},"data":{"trainings":[],"body":{"weight":[],"bodyfat":[]}}},{"username":"nagelkilian05","uid":"google-oauth2|118171829823269176911","settings":{"darkmode":false,"layout":"default"},"data":{"trainings":[],"body":{"weight":[],"bodyfat":[]}}},{"username":"nagelkilian05","uid":"google-oauth2|118171829823269176911","settings":{"darkmode":false,"layout":"default"},"data":{"trainings":[],"body":{"weight":[],"bodyfat":[]}}},{"username":"nagelkilian05","uid":"google-oauth2|118171829823269176911","settings":{"darkmode":false,"layout":"default"},"data":{"trainings":[],"body":{"weight":[],"bodyfat":[]}}},{"username":"nagelkilian05","uid":"google-oauth2|118171829823269176911","settings":{"darkmode":false,"layout":"default"},"data":{"trainings":[],"body":{"weight":[],"bodyfat":[]}}},{"username":"nagelkilian05","uid":"google-oauth2|118171829823269176911","settings":{"darkmode":false,"layout":"default"},"data":{"trainings":[],"body":{"weight":[],"bodyfat":[]}}},{"username":"perfuze1","uid":"google-oauth2|103688329274937160384","settings":{"darkmode":false,"layout":"default"},"data":{"trainings":[],"body":{"weight":[],"bodyfat":[]}}},{"username":"nagelkilian05","uid":"google-oauth2|118171829823269176911","settings":{"darkmode":false,"layout":"default"},"data":{"trainings":[],"body":{"weight":[],"bodyfat":[]}}},{"username":"nagelkilian05","uid":"google-oauth2|118171829823269176911","settings":{"darkmode":false,"layout":"default"},"data":{"trainings":[],"body":{"weight":[],"bodyfat":[]}}},{"username":"zskorpioxfr","uid":"google-oauth2|108677820314655042962","settings":{"darkmode":false,"layout":"default"},"data":{"trainings":[],"body":{"weight":[],"bodyfat":[]}}},{"username":"zskorpioxfr","uid":"google-oauth2|108677820314655042962","settings":{"darkmode":false,"layout":"default"},"data":{"trainings":[],"body":{"weight":[],"bodyfat":[]}}},{"username":"zskorpioxfr","uid":"google-oauth2|108677820314655042962","settings":{"darkmode":false,"layout":"default"},"data":{"trainings":[],"body":{"weight":[],"bodyfat":[]}}},{"username":"zskorpioxfr","uid":"google-oauth2|108677820314655042962","settings":{"darkmode":false,"layout":"default"},"data":{"trainings":[],"body":{"weight":[],"bodyfat":[]}}},{"username":"zskorpioxfr","uid":"google-oauth2|108677820314655042962","settings":{"darkmode":false,"layout":"default"},"data":{"trainings":[],"body":{"weight":[],"bodyfat":[]}}},{"username":"zskorpioxfr","uid":"google-oauth2|108677820314655042962","settings":{"darkmode":false,"layout":"default"},"data":{"trainings":[],"body":{"weight":[],"bodyfat":[]}}},{"username":"zskorpioxfr","uid":"google-oauth2|108677820314655042962","settings":{"darkmode":false,"layout":"default"},"data":{"trainings":[],"body":{"weight":[],"bodyfat":[]}}},{"username":"zskorpioxfr","uid":"google-oauth2|108677820314655042962","settings":{"darkmode":false,"layout":"default"},"data":{"trainings":[],"body":{"weight":[],"bodyfat":[]}}},{"username":"zskorpioxfr","uid":"google-oauth2|108677820314655042962","settings":{"darkmode":false,"layout":"default"},"data":{"trainings":[],"body":{"weight":[],"bodyfat":[]}}},{"username":"zskorpioxfr","uid":"google-oauth2|108677820314655042962","settings":{"darkmode":false,"layout":"default"},"data":{"trainings":[],"body":{"weight":[],"bodyfat":[]}}},{"username":"zskorpioxfr","uid":"google-oauth2|108677820314655042962","settings":{"darkmode":false,"layout":"default"},"data":{"trainings":[],"body":{"weight":[],"bodyfat":[]}}},{"username":"zskorpioxfr","uid":"google-oauth2|108677820314655042962","settings":{"darkmode":false,"layout":"default"},"data":{"trainings":[],"body":{"weight":[],"bodyfat":[]}}},{"username":"zskorpioxfr","uid":"google-oauth2|108677820314655042962","settings":{"darkmode":false,"layout":"default"},"data":{"trainings":[],"body":{"weight":[],"bodyfat":[]}}},{"username":"zskorpioxfr","uid":"google-oauth2|108677820314655042962","settings":{"darkmode":false,"layout":"default"},"data":{"trainings":[],"body":{"weight":[],"bodyfat":[]}}},{"username":"zskorpioxfr","uid":"google-oauth2|108677820314655042962","settings":{"darkmode":false,"layout":"default"},"data":{"trainings":[],"body":{"weight":[],"bodyfat":[]}}},{"username":"zskorpioxfr","uid":"google-oauth2|108677820314655042962","settings":{"darkmode":false,"layout":"default"},"data":{"trainings":[],"body":{"weight":[],"bodyfat":[]}}},{"username":"zskorpioxfr","uid":"google-oauth2|108677820314655042962","settings":{"darkmode":false,"layout":"default"},"data":{"trainings":[],"body":{"weight":[],"bodyfat":[]}}},{"username":"zskorpioxfr","uid":"google-oauth2|108677820314655042962","settings":{"darkmode":false,"layout":"default"},"data":{"trainings":[],"body":{"weight":[],"bodyfat":[]}}},{"username":"zskorpioxfr","uid":"google-oauth2|108677820314655042962","settings":{"darkmode":false,"layout":"default"},"data":{"trainings":[],"body":{"weight":[],"bodyfat":[]}}},{"username":"zskorpioxfr","uid":"google-oauth2|108677820314655042962","settings":{"darkmode":false,"layout":"default"},"data":{"trainings":[],"body":{"weight":[],"bodyfat":[]}}},{"username":"zskorpioxfr","uid":"google-oauth2|108677820314655042962","settings":{"darkmode":false,"layout":"default"},"data":{"trainings":[],"body":{"weight":[],"bodyfat":[]}}},{"username":"zskorpioxfr","uid":"google-oauth2|108677820314655042962","settings":{"darkmode":false,"layout":"default"},"data":{"trainings":[],"body":{"weight":[],"bodyfat":[]}}},{"username":"zskorpioxfr","uid":"google-oauth2|108677820314655042962","settings":{"darkmode":false,"layout":"default"},"data":{"trainings":[],"body":{"weight":[],"bodyfat":[]}}},{"username":"zskorpioxfr","uid":"google-oauth2|108677820314655042962","settings":{"darkmode":false,"layout":"default"},"data":{"trainings":[],"body":{"weight":[],"bodyfat":[]}}},{"username":"zskorpioxfr","uid":"google-oauth2|108677820314655042962","settings":{"darkmode":false,"layout":"default"},"data":{"trainings":[],"body":{"weight":[],"bodyfat":[]}}},{"username":"zskorpioxfr","uid":"google-oauth2|108677820314655042962","settings":{"darkmode":false,"layout":"default"},"data":{"trainings":[],"body":{"weight":[],"bodyfat":[]}}},{"username":"zskorpioxfr","uid":"google-oauth2|108677820314655042962","settings":{"darkmode":false,"layout":"default"},"data":{"trainings":[],"body":{"weight":[],"bodyfat":[]}}},{"username":"zskorpioxfr","uid":"google-oauth2|108677820314655042962","settings":{"darkmode":false,"layout":"default"},"data":{"trainings":[],"body":{"weight":[],"bodyfat":[]}}},{"username":"zskorpioxfr","uid":"google-oauth2|108677820314655042962","settings":{"darkmode":false,"layout":"default"},"data":{"trainings":[],"body":{"weight":[],"bodyfat":[]}}},{"username":"zskorpioxfr","uid":"google-oauth2|108677820314655042962","settings":{"darkmode":false,"layout":"default"},"data":{"trainings":[],"body":{"weight":[],"bodyfat":[]}}},{"username":"zskorpioxfr","uid":"google-oauth2|108677820314655042962","settings":{"darkmode":false,"layout":"default"},"data":{"trainings":[],"body":{"weight":[],"bodyfat":[]}}},{"username":"nagelkilian05","uid":"google-oauth2|118171829823269176911","settings":{"darkmode":false,"layout":"default"},"data":{"trainings":[],"body":{"weight":[],"bodyfat":[]}}},{"username":"nagelkilian05","uid":"google-oauth2|118171829823269176911","settings":{"darkmode":false,"layout":"default"},"data":{"trainings":[],"body":{"weight":[],"bodyfat":[]}}},{"username":"nagelkilian05","uid":"google-oauth2|118171829823269176911","settings":{"darkmode":false,"layout":"default"},"data":{"trainings":[],"body":{"weight":[],"bodyfat":[]}}},{"username":"nagelkilian05","uid":"google-oauth2|118171829823269176911","settings":{"darkmode":false,"layout":"default"},"data":{"trainings":[],"body":{"weight":[],"bodyfat":[]}}},{"username":"nagelkilian05","uid":"google-oauth2|118171829823269176911","settings":{"darkmode":false,"layout":"default"},"data":{"trainings":[],"body":{"weight":[],"bodyfat":[]}}},{"username":"nagelkilian05","uid":"google-oauth2|118171829823269176911","settings":{"darkmode":false,"layout":"default"},"data":{"trainings":[],"body":{"weight":[],"bodyfat":[]}}},{"username":"nagelkilian05","uid":"google-oauth2|118171829823269176911","settings":{"darkmode":false,"layout":"default"},"data":{"trainings":[],"body":{"weight":[],"bodyfat":[]}}},{"username":"nagelkilian05","uid":"google-oauth2|118171829823269176911","settings":{"darkmode":false,"layout":"default"},"data":{"trainings":[],"body":{"weight":[],"bodyfat":[]}}},{"username":"nagelkilian05","uid":"google-oauth2|118171829823269176911","settings":{"darkmode":false,"layout":"default"},"data":{"trainings":[],"body":{"weight":[],"bodyfat":[]}}},{"username":"zskorpioxfr","uid":"google-oauth2|108677820314655042962","settings":{"darkmode":false,"layout":"default"},"data":{"trainings":[],"body":{"weight":[],"bodyfat":[]}}},{"username":"zskorpioxfr","uid":"google-oauth2|108677820314655042962","settings":{"darkmode":false,"layout":"default"},"data":{"trainings":[],"body":{"weight":[],"bodyfat":[]}}},{"username":"zskorpioxfr","uid":"google-oauth2|108677820314655042962","settings":{"darkmode":false,"layout":"default"},"data":{"trainings":[],"body":{"weight":[],"bodyfat":[]}}},{"username":"zskorpioxfr","uid":"google-oauth2|108677820314655042962","settings":{"darkmode":false,"layout":"default"},"data":{"trainings":[],"body":{"weight":[],"bodyfat":[]}}},{"username":"zskorpioxfr","uid":"google-oauth2|108677820314655042962","settings":{"darkmode":false,"layout":"default"},"data":{"trainings":[],"body":{"weight":[],"bodyfat":[]}}},{"username":"zskorpioxfr","uid":"google-oauth2|108677820314655042962","settings":{"darkmode":false,"layout":"default"},"data":{"trainings":[],"body":{"weight":[],"bodyfat":[]}}},{"username":"zskorpioxfr","uid":"google-oauth2|108677820314655042962","settings":{"darkmode":false,"layout":"default"},"data":{"trainings":[],"body":{"weight":[],"bodyfat":[]}}},{"username":"zskorpioxfr","uid":"google-oauth2|108677820314655042962","settings":{"darkmode":false,"layout":"default"},"data":{"trainings":[],"body":{"weight":[],"bodyfat":[]}}},{"username":"zskorpioxfr","uid":"google-oauth2|108677820314655042962","settings":{"darkmode":false,"layout":"default"},"data":{"trainings":[],"body":{"weight":[],"bodyfat":[]}}},{"username":"zskorpioxfr","uid":"google-oauth2|108677820314655042962","settings":{"darkmode":false,"layout":"default"},"data":{"trainings":[],"body":{"weight":[],"bodyfat":[]}}},{"username":"zskorpioxfr","uid":"google-oauth2|108677820314655042962","settings":{"darkmode":false,"layout":"default"},"data":{"trainings":[],"body":{"weight":[],"bodyfat":[]}}},{"username":"zskorpioxfr","uid":"google-oauth2|108677820314655042962","settings":{"darkmode":false,"layout":"default"},"data":{"trainings":[],"body":{"weight":[],"bodyfat":[]}}},{"username":"zskorpioxfr","uid":"google-oauth2|108677820314655042962","settings":{"darkmode":false,"layout":"default"},"data":{"trainings":[],"body":{"weight":[],"bodyfat":[]}}},{"username":"zskorpioxfr","uid":"google-oauth2|108677820314655042962","settings":{"darkmode":false,"layout":"default"},"data":{"trainings":[],"body":{"weight":[],"bodyfat":[]}}},{"username":"zskorpioxfr","uid":"google-oauth2|108677820314655042962","settings":{"darkmode":false,"layout":"default"},"data":{"trainings":[],"body":{"weight":[],"bodyfat":[]}}},{"username":"zskorpioxfr","uid":"google-oauth2|108677820314655042962","settings":{"darkmode":false,"layout":"default"},"data":{"trainings":[],"body":{"weight":[],"bodyfat":[]}}},{"username":"zskorpioxfr","uid":"google-oauth2|108677820314655042962","settings":{"darkmode":false,"layout":"default"},"data":{"trainings":[],"body":{"weight":[],"bodyfat":[]}}},{"username":"zskorpioxfr","uid":"google-oauth2|108677820314655042962","settings":{"darkmode":false,"layout":"default"},"data":{"trainings":[],"body":{"weight":[],"bodyfat":[]}}},{"username":"zskorpioxfr","uid":"google-oauth2|108677820314655042962","settings":{"darkmode":false,"layout":"default"},"data":{"trainings":[],"body":{"weight":[],"bodyfat":[]}}},{"username":"zskorpioxfr","uid":"google-oauth2|108677820314655042962","settings":{"darkmode":false,"layout":"default"},"data":{"trainings":[],"body":{"weight":[],"bodyfat":[]}}},{"username":"zskorpioxfr","uid":"google-oauth2|108677820314655042962","settings":{"darkmode":false,"layout":"default"},"data":{"trainings":[],"body":{"weight":[],"bodyfat":[]}}}]